setup.py
UploadView.egg-info/PKG-INFO
UploadView.egg-info/SOURCES.txt
UploadView.egg-info/dependency_links.txt
UploadView.egg-info/entry_points.txt
UploadView.egg-info/not-zip-safe
UploadView.egg-info/requires.txt
UploadView.egg-info/top_level.txt
uploader/__init__.py
uploader/dispatcher.py
uploader/factory.py
uploader/handlers.py