Metadata-Version: 1.0
Name: UploadView
Version: 0.2.7
Summary: a file uploader app
Home-page: http://k0s.org/hg/uploader
Author: Ethan Jucovy
Author-email: UNKNOWN
License: GPL
Platform: UNKNOWN
